CHANGES.rst
LICENSE.txt
MANIFEST.in
README.rst
dev-requirements.txt
requirements.txt
setup.py
version.py
Delorean.egg-info/PKG-INFO
Delorean.egg-info/SOURCES.txt
Delorean.egg-info/dependency_links.txt
Delorean.egg-info/pbr.json
Delorean.egg-info/requires.txt
Delorean.egg-info/top_level.txt
delorean/__init__.py
delorean/dates.py
delorean/exceptions.py
delorean/interface.py
docs/contribution.rst
docs/index.rst
docs/install.rst
docs/interface.rst
docs/license.rst
docs/philosophy.rst
docs/quickstart.rst