Metadata-Version: 1.1
Name: Delorean
Version: 0.6.0
Summary: library for manipulating datetimes with ease and clarity
Home-page: https://github.com/myusuf3/delorean
Author: Mahdi Yusuf
Author-email: yusuf.mahdi@gmail.com
License: MIT license
Platform: UNKNOWN
Classifier: Development Status :: 4 - Beta
Classifier: Intended Audience :: Developers
Classifier: Natural Language :: English
Classifier: License :: OSI Approved :: MIT License
Classifier: Programming Language :: Python
Classifier: Programming Language :: Python :: 2.6
Classifier: Programming Language :: Python :: 2.7
Classifier: Programming Language :: Python :: 3
Classifier: Programming Language :: Python :: 3.1
Classifier: Programming Language :: Python :: 3.3
Classifier: Programming Language :: Python :: 3.4
